webarena_verified/__init__.py
webarena_verified/__main__.py
webarena_verified/utils.py
webarena_verified/api/__init__.py
webarena_verified/api/webarena_verified.py
webarena_verified/api/internal/__init__.py
webarena_verified/api/internal/data_reader.py
webarena_verified/api/internal/evaluator.py
webarena_verified/api/internal/patch_manager.py
webarena_verified/api/internal/submission_handler.py
webarena_verified/api/internal/subsets_manager.py
webarena_verified/core/__init__.py
webarena_verified/core/evaluation/__init__.py
webarena_verified/core/evaluation/value_comparator.py
webarena_verified/core/evaluation/value_normalizer.py
webarena_verified/core/evaluation/data_types/__init__.py
webarena_verified/core/evaluation/data_types/base.py
webarena_verified/core/evaluation/data_types/base64_string.py
webarena_verified/core/evaluation/data_types/boolean.py
webarena_verified/core/evaluation/data_types/coordinates.py
webarena_verified/core/evaluation/data_types/currency.py
webarena_verified/core/evaluation/data_types/date.py
webarena_verified/core/evaluation/data_types/distance.py
webarena_verified/core/evaluation/data_types/duration.py
webarena_verified/core/evaluation/data_types/empty.py
webarena_verified/core/evaluation/data_types/full_address.py
webarena_verified/core/evaluation/data_types/json_string.py
webarena_verified/core/evaluation/data_types/location_name.py
webarena_verified/core/evaluation/data_types/markdown_string.py
webarena_verified/core/evaluation/data_types/month.py
webarena_verified/core/evaluation/data_types/number.py
webarena_verified/core/evaluation/data_types/string.py
webarena_verified/core/evaluation/data_types/string_list.py
webarena_verified/core/evaluation/data_types/url.py
webarena_verified/core/evaluation/evaluators/__init__.py
webarena_verified/core/evaluation/evaluators/agent_response_evaluator.py
webarena_verified/core/evaluation/evaluators/base.py
webarena_verified/core/evaluation/evaluators/network_event_evaluator.py
webarena_verified-1.0.0.dist-info/METADATA
webarena_verified-1.0.0.dist-info/WHEEL
webarena_verified-1.0.0.dist-info/entry_points.txt
webarena_verified-1.0.0.dist-info/licenses/LICENSE
webarena_verified-1.0.0.dist-info/RECORD
