Metadata-Version: 2.4
Name: webarena-verified
Version: 1.0.0
Summary: A verified version of the WebArena Benchmark
Author-email: Amine Elhattami <amine.elhattami@servicenow.com>
License-File: LICENSE
Requires-Python: >=3.11
Requires-Dist: beautifulsoup4==4.14.2
Requires-Dist: compact-json==1.8.1
Requires-Dist: geographiclib==2.1
Requires-Dist: geopy==2.4.1
Requires-Dist: jsonpath-ng==1.7.0
Requires-Dist: pint==0.25
Requires-Dist: price-parser==0.5.0
Requires-Dist: pydantic==2.12.0
Requires-Dist: python-dateutil==2.9.0.post0
Requires-Dist: pytimeparse2==1.7.1
Requires-Dist: thefuzz>=0.22.1
Requires-Dist: unidecode==1.4.0
Requires-Dist: url-normalize==2.2.1
Requires-Dist: us==3.2.0
Requires-Dist: usaddress-scourgify==0.6.0
Requires-Dist: usaddress==0.5.16
Requires-Dist: word2number==1.1
Provides-Extra: contributing
Requires-Dist: click>=8.3.0; extra == 'contributing'
Requires-Dist: litellm>=1.80.5; extra == 'contributing'
Requires-Dist: pydantic-settings>=2.11.0; extra == 'contributing'
Provides-Extra: examples
Requires-Dist: aiohttp>=3.12.15; extra == 'examples'
Requires-Dist: browser-use>=0.8.1; extra == 'examples'
Requires-Dist: browser-use>=0.9.6; extra == 'examples'
Requires-Dist: filelock>=3.16.1; extra == 'examples'
Requires-Dist: jinja2>=3.1.6; extra == 'examples'
Requires-Dist: playwright>=1.55.0; extra == 'examples'
Requires-Dist: requests>=2.32.0; extra == 'examples'
